meteron/__init__.py
meteron/__version__.py
meteron/meteron.py
meteron-0.1.4.dist-info/LICENSE
meteron-0.1.4.dist-info/METADATA
meteron-0.1.4.dist-info/WHEEL
meteron-0.1.4.dist-info/top_level.txt
meteron-0.1.4.dist-info/RECORD
