Metadata-Version: 2.1
Name: meteron
Version: 0.1.4
Summary: Queuing, storage, metering, rate limiting for AI
Home-page: https://meteron.com
Download-URL: https://github.com/meteron-ai/meteron-python
Author: Karolis Rusenas
Author-email: karolis@rusenas.dev
License: Apache License 2.0
Keywords: deep learning,ML,AI
Requires-Python: >=3.8
License-File: LICENSE
Requires-Dist: requests (>=2.28.2)
